{
    "input_path": "temp/8A16.pdf",
    "page_index": 2,
    "model_settings": {
        "use_doc_preprocessor": true,
        "use_seal_recognition": false,
        "use_table_recognition": true,
        "use_formula_recognition": true,
        "use_chart_recognition": false,
        "use_region_detection": true
    },
    "parsing_res_list": [
        {
            "block_label": "text",
            "block_content": "5.5. Продавец имеет право проверить на месте сам или через своих представителейобоснованность претензии.\n",
            "block_bbox": [
                106,
                99,
                1098,
                147
            ]
        },
        {
            "block_label": "text",
            "block_content": "5.6. Покупатель не имеет права отказаться от оплаты товара, в отношении которогопредъявлена претензия.\n",
            "block_bbox": [
                107,
                155,
                1099,
                203
            ]
        },
        {
            "block_label": "text",
            "block_content": "5.7. Покупатель не имеет права ликвидировать или использовать дефектный товар до техпор, пока Продавец не примет решение по претензии.\n",
            "block_bbox": [
                106,
                209,
                1099,
                259
            ]
        },
        {
            "block_label": "text",
            "block_content": "5.8 Продавец должен рассмотреть претензию и информировать Покупателя о своёмрешении не позднее 30 дней от даты получения претензии.\n",
            "block_bbox": [
                106,
                265,
                1100,
                313
            ]
        },
        {
            "block_label": "text",
            "block_content": "5.9. Продавец и Покупатель предпримут все необходимые меры для урегулированияпретензий, если таковые имеются, дружеским путем. В случае возникновения каких-либоспоров между Продавцом и Покупателем в отношении количества и/или качества товара, обасогласныразрешитьпротиворечия через заключение независимойH нейтральнойинспекционной компании, в присутствии представителей Продавца. Продавец извещается пофаксу или электронной почте о возникновении спора в течение 72 часов. В случае неприбытияпредставителя Продавца в течение 24 дней, спор разрешается официальными представителяминезависимой и нейтральной инспекционной компании в его отсутствие. Заключениепредставителей независимой и нейтральной инспекционной компании является окончательными обязательным для обеих сторон. Оплату услуг по получению заключения независимой инейтральной инспекционной компании осуществляет Покупатель.\n",
            "block_bbox": [
                106,
                320,
                1105,
                617
            ]
        },
        {
            "block_label": "text",
            "block_content": "5.10. В случае необходимости возврата рекламационного товара, возврат будетосуществляться на условиях ДАР Жлобин согласно Инкотермс 2010.",
            "block_bbox": [
                106,
                624,
                1099,
                672
            ]
        },
        {
            "block_label": "text",
            "block_content": "5.11. После предоставления официального ответа Покупателю по претензии(рекламации), Покупатель должен в течение 30 календарных дней после его предоставленияизвестить Продавца о закрытии претензии (рекламации), либо предоставить свои комментарии.В случае не предоставления ответа в течение 30 календарных дней претензия (рекламация)аннулируется Продавцом в одностороннем порядке и возмещению не подлежит.",
            "block_bbox": [
                106,
                679,
                1099,
                812
            ]
        },
        {
            "block_label": "paragraph_title",
            "block_content": "VI.СРОКИ И ПОРЯДОК ПОСТАВКИ",
            "block_bbox": [
                364,
                842,
                848,
                863
            ]
        },
        {
            "block_label": "text",
            "block_content": "6.1. Покупатель ежемесячно предоставляет в срок до 10-го числа текущего месяца заявкуна изготовление товара в последующем месяце (в заявке должны быть указаны: номердоговора, наименование товара, ТНПА, количество с разбивкой по маркам и размерам, длина,особые условия, назначение металла, отгрузочные реквизиты).\n",
            "block_bbox": [
                106,
                873,
                1105,
                976
            ]
        },
        {
            "block_label": "text",
            "block_content": "6.2. В случае не предоставления заявки, либо предоставления заявки позднее срока,указанного в пункте 6.1 настоящего договора, Продавец имеет право не принимать даннуюзаявку к исполнению.\n",
            "block_bbox": [
                106,
                983,
                1105,
                1058
            ]
        },
        {
            "block_label": "text",
            "block_content": "6.3. Продавец, в случае принятия заявки, направляет Покупателю Приложение на поставкутовара, а также при необходимости счет на оплату Товара с указанием срока для его оплаты, аПокупатель обязуется оплатить указанную в счете Продавца партию Товара, либо письменносообщить о невозможности произвести оплату. В случае не оплаты в указанный в счете срок,Продавец оставляет за собой право снять с производства заявленный товар, либо реализоватьпроизведенный по заявке Покупателя Товар другому потребителю.",
            "block_bbox": [
                105,
                1066,
                1106,
                1225
            ]
        },
        {
            "block_label": "text",
            "block_content": "6.4. При поставке товара железнодорожным транспортом применяются условия поставкиDАР (Инкотермс 201о). По согласованию сторон допускаются иные условия поставки, которыеоговариваются в Приложениях на поставку товара.\n",
            "block_bbox": [
                106,
                1232,
                1105,
                1307
            ]
        },
        {
            "block_label": "text",
            "block_content": "6.5. При поставке товара автомобильным транспортом применяются условия поставки FСА- Жлобин(Инкотермс 2010).\n",
            "block_bbox": [
                105,
                1314,
                1105,
                1362
            ]
        },
        {
            "block_label": "text",
            "block_content": "6.6. Продавец при отгрузке товара оформляет товаросопроводительные документы:",
            "block_bbox": [
                139,
                1369,
                1012,
                1391
            ]
        },
        {
            "block_label": "text",
            "block_content": "- при отгрузке автомобильным транспортом: товарную накладную, международную накладнуюформы СмR, сертификат (паспорт) качества, сертификат происхождения, счет (счет-фактура,счет-проформа), копию декларации на товар (внешнее представление электронной декларациина товары либо копию декларации на товары, в случае оформления такой декларации вписьменной форме);",
            "block_bbox": [
                105,
                1395,
                1105,
                1528
            ]
        },
        {
            "block_label": "footer",
            "block_content": "24022311 ТОО «АзияМетизКомплект",
            "block_bbox": [
                109,
                1567,
                442,
                1585
            ]
        },
        {
            "block_label": "number",
            "block_content": "3",
            "block_bbox": [
                1082,
                1569,
                1093,
                1584
            ]
        }
    ],
    "doc_preprocessor_res": {
        "input_path": null,
        "page_index": null,
        "model_settings": {
            "use_doc_orientation_classify": false,
            "use_doc_unwarping": false
        },
        "angle": -1
    },
    "layout_det_res": {
        "input_path": null,
        "page_index": null,
        "boxes": [
            {
                "cls_id": 2,
                "label": "text",
                "score": 0.9870384335517883,
                "coordinate": [
                    106.0986328125,
                    320.15655517578125,
                    1105.1829833984375,
                    617.9641723632812
                ]
            },
            {
                "cls_id": 2,
                "label": "text",
                "score": 0.9826623201370239,
                "coordinate": [
                    105.6820068359375,
                    1066.009521484375,
                    1106.0614013671875,
                    1225.2978515625
                ]
            },
            {
                "cls_id": 2,
                "label": "text",
                "score": 0.979023277759552,
                "coordinate": [
                    106.5052490234375,
                    679.3147583007812,
                    1099.9771728515625,
                    812.1970825195312
                ]
            },
            {
                "cls_id": 2,
                "label": "text",
                "score": 0.9760997295379639,
                "coordinate": [
                    106.10260009765625,
                    873.0372924804688,
                    1105.608642578125,
                    976.7529907226562
                ]
            },
            {
                "cls_id": 2,
                "label": "text",
                "score": 0.9680019617080688,
                "coordinate": [
                    106.24713134765625,
                    1232.200439453125,
                    1105.26953125,
                    1307.839111328125
                ]
            },
            {
                "cls_id": 2,
                "label": "text",
                "score": 0.9667403697967529,
                "coordinate": [
                    106.36154174804688,
                    983.6849365234375,
                    1105.7537841796875,
                    1058.6051025390625
                ]
            },
            {
                "cls_id": 2,
                "label": "text",
                "score": 0.9527963399887085,
                "coordinate": [
                    107.1148681640625,
                    155.000732421875,
                    1099.3707275390625,
                    203.17828369140625
                ]
            },
            {
                "cls_id": 2,
                "label": "text",
                "score": 0.9512993693351746,
                "coordinate": [
                    105.70999145507812,
                    1314.0535888671875,
                    1105.150390625,
                    1362.5452880859375
                ]
            },
            {
                "cls_id": 2,
                "label": "text",
                "score": 0.9512219429016113,
                "coordinate": [
                    106.7071533203125,
                    209.90985107421875,
                    1099.10888671875,
                    259.1508483886719
                ]
            },
            {
                "cls_id": 2,
                "label": "text",
                "score": 0.9508665800094604,
                "coordinate": [
                    106.14938354492188,
                    265.42767333984375,
                    1100.271484375,
                    313.595458984375
                ]
            },
            {
                "cls_id": 2,
                "label": "text",
                "score": 0.949349582195282,
                "coordinate": [
                    106.974853515625,
                    624.0087890625,
                    1099.93896484375,
                    672.551025390625
                ]
            },
            {
                "cls_id": 2,
                "label": "text",
                "score": 0.9447842240333557,
                "coordinate": [
                    106.63314819335938,
                    99.26480102539062,
                    1098.7301025390625,
                    147.97042846679688
                ]
            },
            {
                "cls_id": 2,
                "label": "text",
                "score": 0.9314407110214233,
                "coordinate": [
                    105.624755859375,
                    1395.3594970703125,
                    1105.8521728515625,
                    1528.8599853515625
                ]
            },
            {
                "cls_id": 0,
                "label": "paragraph_title",
                "score": 0.9152507781982422,
                "coordinate": [
                    364.1865234375,
                    842.8604736328125,
                    848.8748779296875,
                    863.2315673828125
                ]
            },
            {
                "cls_id": 14,
                "label": "footer",
                "score": 0.8680732250213623,
                "coordinate": [
                    109.10276794433594,
                    1567.525634765625,
                    442.5537109375,
                    1585.8818359375
                ]
            },
            {
                "cls_id": 3,
                "label": "number",
                "score": 0.7930573225021362,
                "coordinate": [
                    1082.988037109375,
                    1569.0123291015625,
                    1093.668212890625,
                    1584.9525146484375
                ]
            },
            {
                "cls_id": 2,
                "label": "text",
                "score": 0.5941458940505981,
                "coordinate": [
                    139.53469848632812,
                    1369.7235107421875,
                    1012.0911865234375,
                    1391.0037841796875
                ]
            }
        ]
    },
    "overall_ocr_res": {
        "input_path": null,
        "page_index": null,
        "model_settings": {
            "use_doc_preprocessor": false,
            "use_textline_orientation": false
        },
        "dt_polys": [
            [
                [
                    167,
                    94
                ],
                [
                    1101,
                    96
                ],
                [
                    1101,
                    124
                ],
                [
                    167,
                    122
                ]
            ],
            [
                [
                    112,
                    124
                ],
                [
                    394,
                    126
                ],
                [
                    394,
                    150
                ],
                [
                    112,
                    148
                ]
            ],
            [
                [
                    166,
                    149
                ],
                [
                    1102,
                    154
                ],
                [
                    1101,
                    182
                ],
                [
                    166,
                    177
                ]
            ],
            [
                [
                    111,
                    182
                ],
                [
                    358,
                    181
                ],
                [
                    358,
                    205
                ],
                [
                    111,
                    206
                ]
            ],
            [
                [
                    166,
                    206
                ],
                [
                    1101,
                    208
                ],
                [
                    1101,
                    235
                ],
                [
                    166,
                    233
                ]
            ],
            [
                [
                    112,
                    236
                ],
                [
                    668,
                    236
                ],
                [
                    668,
                    260
                ],
                [
                    112,
                    260
                ]
            ],
            [
                [
                    165,
                    261
                ],
                [
                    1104,
                    263
                ],
                [
                    1103,
                    290
                ],
                [
                    165,
                    288
                ]
            ],
            [
                [
                    110,
                    292
                ],
                [
                    721,
                    292
                ],
                [
                    721,
                    316
                ],
                [
                    110,
                    316
                ]
            ],
            [
                [
                    166,
                    316
                ],
                [
                    1109,
                    319
                ],
                [
                    1108,
                    346
                ],
                [
                    166,
                    343
                ]
            ],
            [
                [
                    109,
                    346
                ],
                [
                    1108,
                    345
                ],
                [
                    1109,
                    371
                ],
                [
                    109,
                    372
                ]
            ],
            [
                [
                    111,
                    374
                ],
                [
                    1108,
                    374
                ],
                [
                    1108,
                    398
                ],
                [
                    111,
                    398
                ]
            ],
            [
                [
                    111,
                    404
                ],
                [
                    214,
                    404
                ],
                [
                    214,
                    425
                ],
                [
                    111,
                    425
                ]
            ],
            [
                [
                    203,
                    403
                ],
                [
                    376,
                    403
                ],
                [
                    376,
                    427
                ],
                [
                    203,
                    427
                ]
            ],
            [
                [
                    363,
                    401
                ],
                [
                    921,
                    399
                ],
                [
                    921,
                    426
                ],
                [
                    363,
                    428
                ]
            ],
            [
                [
                    927,
                    403
                ],
                [
                    959,
                    403
                ],
                [
                    959,
                    422
                ],
                [
                    927,
                    422
                ]
            ],
            [
                [
                    970,
                    401
                ],
                [
                    1108,
                    401
                ],
                [
                    1108,
                    425
                ],
                [
                    970,
                    425
                ]
            ],
            [
                [
                    109,
                    430
                ],
                [
                    1108,
                    430
                ],
                [
                    1108,
                    454
                ],
                [
                    109,
                    454
                ]
            ],
            [
                [
                    112,
                    458
                ],
                [
                    1108,
                    458
                ],
                [
                    1108,
                    482
                ],
                [
                    112,
                    482
                ]
            ],
            [
                [
                    110,
                    484
                ],
                [
                    1109,
                    484
                ],
                [
                    1109,
                    510
                ],
                [
                    110,
                    510
                ]
            ],
            [
                [
                    110,
                    512
                ],
                [
                    1108,
                    512
                ],
                [
                    1108,
                    536
                ],
                [
                    110,
                    536
                ]
            ],
            [
                [
                    108,
                    539
                ],
                [
                    1108,
                    538
                ],
                [
                    1109,
                    565
                ],
                [
                    108,
                    566
                ]
            ],
            [
                [
                    108,
                    565
                ],
                [
                    1109,
                    568
                ],
                [
                    1108,
                    595
                ],
                [
                    108,
                    592
                ]
            ],
            [
                [
                    111,
                    596
                ],
                [
                    797,
                    596
                ],
                [
                    797,
                    620
                ],
                [
                    111,
                    620
                ]
            ],
            [
                [
                    166,
                    620
                ],
                [
                    1103,
                    623
                ],
                [
                    1102,
                    649
                ],
                [
                    166,
                    646
                ]
            ],
            [
                [
                    110,
                    649
                ],
                [
                    826,
                    647
                ],
                [
                    826,
                    674
                ],
                [
                    110,
                    676
                ]
            ],
            [
                [
                    164,
                    674
                ],
                [
                    1104,
                    678
                ],
                [
                    1103,
                    706
                ],
                [
                    164,
                    702
                ]
            ],
            [
                [
                    110,
                    704
                ],
                [
                    1103,
                    705
                ],
                [
                    1103,
                    732
                ],
                [
                    110,
                    731
                ]
            ],
            [
                [
                    109,
                    732
                ],
                [
                    1100,
                    733
                ],
                [
                    1100,
                    760
                ],
                [
                    109,
                    759
                ]
            ],
            [
                [
                    109,
                    759
                ],
                [
                    1100,
                    760
                ],
                [
                    1100,
                    786
                ],
                [
                    109,
                    785
                ]
            ],
            [
                [
                    110,
                    788
                ],
                [
                    944,
                    789
                ],
                [
                    944,
                    813
                ],
                [
                    110,
                    812
                ]
            ],
            [
                [
                    366,
                    840
                ],
                [
                    415,
                    840
                ],
                [
                    415,
                    867
                ],
                [
                    366,
                    867
                ]
            ],
            [
                [
                    439,
                    842
                ],
                [
                    849,
                    842
                ],
                [
                    849,
                    866
                ],
                [
                    439,
                    866
                ]
            ],
            [
                [
                    166,
                    869
                ],
                [
                    1108,
                    873
                ],
                [
                    1107,
                    900
                ],
                [
                    166,
                    896
                ]
            ],
            [
                [
                    108,
                    900
                ],
                [
                    1107,
                    901
                ],
                [
                    1106,
                    924
                ],
                [
                    108,
                    923
                ]
            ],
            [
                [
                    110,
                    925
                ],
                [
                    1105,
                    925
                ],
                [
                    1105,
                    952
                ],
                [
                    110,
                    952
                ]
            ],
            [
                [
                    112,
                    955
                ],
                [
                    759,
                    955
                ],
                [
                    759,
                    979
                ],
                [
                    112,
                    979
                ]
            ],
            [
                [
                    151,
                    979
                ],
                [
                    1107,
                    983
                ],
                [
                    1106,
                    1010
                ],
                [
                    151,
                    1006
                ]
            ],
            [
                [
                    108,
                    1008
                ],
                [
                    1108,
                    1010
                ],
                [
                    1107,
                    1037
                ],
                [
                    108,
                    1035
                ]
            ],
            [
                [
                    111,
                    1040
                ],
                [
                    338,
                    1040
                ],
                [
                    338,
                    1060
                ],
                [
                    111,
                    1060
                ]
            ],
            [
                [
                    151,
                    1061
                ],
                [
                    1108,
                    1065
                ],
                [
                    1107,
                    1092
                ],
                [
                    151,
                    1088
                ]
            ],
            [
                [
                    109,
                    1093
                ],
                [
                    1108,
                    1093
                ],
                [
                    1108,
                    1117
                ],
                [
                    109,
                    1117
                ]
            ],
            [
                [
                    108,
                    1118
                ],
                [
                    1108,
                    1119
                ],
                [
                    1107,
                    1146
                ],
                [
                    108,
                    1145
                ]
            ],
            [
                [
                    110,
                    1147
                ],
                [
                    1106,
                    1149
                ],
                [
                    1105,
                    1173
                ],
                [
                    110,
                    1171
                ]
            ],
            [
                [
                    111,
                    1176
                ],
                [
                    1107,
                    1176
                ],
                [
                    1107,
                    1199
                ],
                [
                    111,
                    1199
                ]
            ],
            [
                [
                    111,
                    1203
                ],
                [
                    807,
                    1203
                ],
                [
                    807,
                    1227
                ],
                [
                    111,
                    1227
                ]
            ],
            [
                [
                    150,
                    1228
                ],
                [
                    1109,
                    1231
                ],
                [
                    1108,
                    1258
                ],
                [
                    150,
                    1255
                ]
            ],
            [
                [
                    109,
                    1256
                ],
                [
                    1108,
                    1259
                ],
                [
                    1107,
                    1285
                ],
                [
                    109,
                    1282
                ]
            ],
            [
                [
                    112,
                    1287
                ],
                [
                    638,
                    1287
                ],
                [
                    638,
                    1311
                ],
                [
                    112,
                    1311
                ]
            ],
            [
                [
                    150,
                    1309
                ],
                [
                    1108,
                    1311
                ],
                [
                    1107,
                    1340
                ],
                [
                    150,
                    1338
                ]
            ],
            [
                [
                    109,
                    1337
                ],
                [
                    407,
                    1338
                ],
                [
                    407,
                    1365
                ],
                [
                    109,
                    1364
                ]
            ],
            [
                [
                    146,
                    1367
                ],
                [
                    1011,
                    1370
                ],
                [
                    1011,
                    1394
                ],
                [
                    146,
                    1391
                ]
            ],
            [
                [
                    107,
                    1396
                ],
                [
                    1106,
                    1398
                ],
                [
                    1105,
                    1421
                ],
                [
                    107,
                    1419
                ]
            ],
            [
                [
                    111,
                    1423
                ],
                [
                    1106,
                    1425
                ],
                [
                    1105,
                    1449
                ],
                [
                    111,
                    1447
                ]
            ],
            [
                [
                    110,
                    1451
                ],
                [
                    1107,
                    1452
                ],
                [
                    1106,
                    1475
                ],
                [
                    110,
                    1474
                ]
            ],
            [
                [
                    111,
                    1479
                ],
                [
                    1107,
                    1479
                ],
                [
                    1107,
                    1502
                ],
                [
                    111,
                    1502
                ]
            ],
            [
                [
                    112,
                    1508
                ],
                [
                    322,
                    1508
                ],
                [
                    322,
                    1529
                ],
                [
                    112,
                    1529
                ]
            ],
            [
                [
                    110,
                    1566
                ],
                [
                    446,
                    1568
                ],
                [
                    446,
                    1588
                ],
                [
                    110,
                    1586
                ]
            ],
            [
                [
                    1079,
                    1564
                ],
                [
                    1101,
                    1564
                ],
                [
                    1101,
                    1591
                ],
                [
                    1079,
                    1591
                ]
            ]
        ],
        "text_det_params": {
            "limit_side_len": 736,
            "limit_type": "min",
            "thresh": 0.3,
            "max_side_limit": 4000,
            "box_thresh": 0.6,
            "unclip_ratio": 1.5
        },
        "text_type": "general",
        "textline_orientation_angles": [
            -1,
            -1,
            -1,
            -1,
            -1,
            -1,
            -1,
            -1,
            -1,
            -1,
            -1,
            -1,
            -1,
            -1,
            -1,
            -1,
            -1,
            -1,
            -1,
            -1,
            -1,
            -1,
            -1,
            -1,
            -1,
            -1,
            -1,
            -1,
            -1,
            -1,
            -1,
            -1,
            -1,
            -1,
            -1,
            -1,
            -1,
            -1,
            -1,
            -1,
            -1,
            -1,
            -1,
            -1,
            -1,
            -1,
            -1,
            -1,
            -1,
            -1,
            -1,
            -1,
            -1,
            -1,
            -1,
            -1,
            -1,
            -1
        ],
        "text_rec_score_thresh": 0.0,
        "return_word_box": false,
        "rec_texts": [
            "5.5. Продавец имеет право проверить на месте сам или через своих представителей",
            "обоснованность претензии.",
            "5.6. Покупатель не имеет права отказаться от оплаты товара, в отношении которого",
            "предъявлена претензия.",
            "5.7. Покупатель не имеет права ликвидировать или использовать дефектный товар до тех",
            "пор, пока Продавец не примет решение по претензии.",
            "5.8 Продавец должен рассмотреть претензию и информировать Покупателя о своём",
            "решении не позднее 30 дней от даты получения претензии.",
            "5.9. Продавец и Покупатель предпримут все необходимые меры для урегулирования",
            "претензий, если таковые имеются, дружеским путем. В случае возникновения каких-либо",
            "споров между Продавцом и Покупателем в отношении количества и/или качества товара, оба",
            "согласны",
            "разрешить",
            "противоречия через заключение независимой",
            "H",
            "нейтральной",
            "инспекционной компании, в присутствии представителей Продавца. Продавец извещается по",
            "факсу или электронной почте о возникновении спора в течение 72 часов. В случае неприбытия",
            "представителя Продавца в течение 24 дней, спор разрешается официальными представителями",
            "независимой и нейтральной инспекционной компании в его отсутствие. Заключение",
            "представителей независимой и нейтральной инспекционной компании является окончательным",
            "и обязательным для обеих сторон. Оплату услуг по получению заключения независимой и",
            "нейтральной инспекционной компании осуществляет Покупатель.",
            "5.10. В случае необходимости возврата рекламационного товара, возврат будет",
            "осуществляться на условиях ДАР Жлобин согласно Инкотермс 2010.",
            "5.11. После предоставления официального ответа Покупателю по претензии",
            "(рекламации), Покупатель должен в течение 30 календарных дней после его предоставления",
            "известить Продавца о закрытии претензии (рекламации), либо предоставить свои комментарии.",
            "В случае не предоставления ответа в течение 30 календарных дней претензия (рекламация)",
            "аннулируется Продавцом в одностороннем порядке и возмещению не подлежит.",
            "VI.",
            "СРОКИ И ПОРЯДОК ПОСТАВКИ",
            "6.1. Покупатель ежемесячно предоставляет в срок до 10-го числа текущего месяца заявку",
            "на изготовление товара в последующем месяце (в заявке должны быть указаны: номер",
            "договора, наименование товара, ТНПА, количество с разбивкой по маркам и размерам, длина,",
            "особые условия, назначение металла, отгрузочные реквизиты).",
            "6.2. В случае не предоставления заявки, либо предоставления заявки позднее срока,",
            "указанного в пункте 6.1 настоящего договора, Продавец имеет право не принимать данную",
            "заявку к исполнению.",
            "6.3. Продавец, в случае принятия заявки, направляет Покупателю Приложение на поставку",
            "товара, а также при необходимости счет на оплату Товара с указанием срока для его оплаты, а",
            "Покупатель обязуется оплатить указанную в счете Продавца партию Товара, либо письменно",
            "сообщить о невозможности произвести оплату. В случае не оплаты в указанный в счете срок,",
            "Продавец оставляет за собой право снять с производства заявленный товар, либо реализовать",
            "произведенный по заявке Покупателя Товар другому потребителю.",
            "6.4. При поставке товара железнодорожным транспортом применяются условия поставки",
            "DАР (Инкотермс 201о). По согласованию сторон допускаются иные условия поставки, которые",
            "оговариваются в Приложениях на поставку товара.",
            "6.5. При поставке товара автомобильным транспортом применяются условия поставки FСА",
            "- Жлобин(Инкотермс 2010).",
            "6.6. Продавец при отгрузке товара оформляет товаросопроводительные документы:",
            "- при отгрузке автомобильным транспортом: товарную накладную, международную накладную",
            "формы СмR, сертификат (паспорт) качества, сертификат происхождения, счет (счет-фактура,",
            "счет-проформа), копию декларации на товар (внешнее представление электронной декларации",
            "на товары либо копию декларации на товары, в случае оформления такой декларации в",
            "письменной форме);",
            "24022311 ТОО «АзияМетизКомплект",
            "3"
        ],
        "rec_scores": [
            0.9799327850341797,
            0.9814285039901733,
            0.9808746576309204,
            0.9673985838890076,
            0.9844318628311157,
            0.9828175902366638,
            0.9811743497848511,
            0.9789412021636963,
            0.976412296295166,
            0.9768617153167725,
            0.9800041317939758,
            0.9616037607192993,
            0.9896328449249268,
            0.9697444438934326,
            0.6278825998306274,
            0.9910186529159546,
            0.9815957546234131,
            0.9799403548240662,
            0.9875365495681763,
            0.9585034251213074,
            0.9930163621902466,
            0.9741476774215698,
            0.9793524742126465,
            0.9705250859260559,
            0.9625210762023926,
            0.9814152121543884,
            0.9834825992584229,
            0.9798375964164734,
            0.9804362654685974,
            0.9893200993537903,
            0.8268705010414124,
            0.9767554402351379,
            0.981053352355957,
            0.9750995635986328,
            0.9645772576332092,
            0.9656019806861877,
            0.9782689213752747,
            0.9707189202308655,
            0.9729586839675903,
            0.9789162874221802,
            0.9767611026763916,
            0.9842487573623657,
            0.9703311920166016,
            0.9753592610359192,
            0.9827816486358643,
            0.9869611859321594,
            0.9698994159698486,
            0.9893404245376587,
            0.9874403476715088,
            0.940065324306488,
            0.9869861602783203,
            0.977238118648529,
            0.9654684066772461,
            0.983897864818573,
            0.965091347694397,
            0.9670359492301941,
            0.9375016093254089,
            0.9963802695274353
        ],
        "rec_polys": [
            [
                [
                    167,
                    94
                ],
                [
                    1101,
                    96
                ],
                [
                    1101,
                    124
                ],
                [
                    167,
                    122
                ]
            ],
            [
                [
                    112,
                    124
                ],
                [
                    394,
                    126
                ],
                [
                    394,
                    150
                ],
                [
                    112,
                    148
                ]
            ],
            [
                [
                    166,
                    149
                ],
                [
                    1102,
                    154
                ],
                [
                    1101,
                    182
                ],
                [
                    166,
                    177
                ]
            ],
            [
                [
                    111,
                    182
                ],
                [
                    358,
                    181
                ],
                [
                    358,
                    205
                ],
                [
                    111,
                    206
                ]
            ],
            [
                [
                    166,
                    206
                ],
                [
                    1101,
                    208
                ],
                [
                    1101,
                    235
                ],
                [
                    166,
                    233
                ]
            ],
            [
                [
                    112,
                    236
                ],
                [
                    668,
                    236
                ],
                [
                    668,
                    260
                ],
                [
                    112,
                    260
                ]
            ],
            [
                [
                    165,
                    261
                ],
                [
                    1104,
                    263
                ],
                [
                    1103,
                    290
                ],
                [
                    165,
                    288
                ]
            ],
            [
                [
                    110,
                    292
                ],
                [
                    721,
                    292
                ],
                [
                    721,
                    316
                ],
                [
                    110,
                    316
                ]
            ],
            [
                [
                    166,
                    316
                ],
                [
                    1109,
                    319
                ],
                [
                    1108,
                    346
                ],
                [
                    166,
                    343
                ]
            ],
            [
                [
                    109,
                    346
                ],
                [
                    1108,
                    345
                ],
                [
                    1109,
                    371
                ],
                [
                    109,
                    372
                ]
            ],
            [
                [
                    111,
                    374
                ],
                [
                    1108,
                    374
                ],
                [
                    1108,
                    398
                ],
                [
                    111,
                    398
                ]
            ],
            [
                [
                    111,
                    404
                ],
                [
                    214,
                    404
                ],
                [
                    214,
                    425
                ],
                [
                    111,
                    425
                ]
            ],
            [
                [
                    203,
                    403
                ],
                [
                    376,
                    403
                ],
                [
                    376,
                    427
                ],
                [
                    203,
                    427
                ]
            ],
            [
                [
                    363,
                    401
                ],
                [
                    921,
                    399
                ],
                [
                    921,
                    426
                ],
                [
                    363,
                    428
                ]
            ],
            [
                [
                    927,
                    403
                ],
                [
                    959,
                    403
                ],
                [
                    959,
                    422
                ],
                [
                    927,
                    422
                ]
            ],
            [
                [
                    970,
                    401
                ],
                [
                    1108,
                    401
                ],
                [
                    1108,
                    425
                ],
                [
                    970,
                    425
                ]
            ],
            [
                [
                    109,
                    430
                ],
                [
                    1108,
                    430
                ],
                [
                    1108,
                    454
                ],
                [
                    109,
                    454
                ]
            ],
            [
                [
                    112,
                    458
                ],
                [
                    1108,
                    458
                ],
                [
                    1108,
                    482
                ],
                [
                    112,
                    482
                ]
            ],
            [
                [
                    110,
                    484
                ],
                [
                    1109,
                    484
                ],
                [
                    1109,
                    510
                ],
                [
                    110,
                    510
                ]
            ],
            [
                [
                    110,
                    512
                ],
                [
                    1108,
                    512
                ],
                [
                    1108,
                    536
                ],
                [
                    110,
                    536
                ]
            ],
            [
                [
                    108,
                    539
                ],
                [
                    1108,
                    538
                ],
                [
                    1109,
                    565
                ],
                [
                    108,
                    566
                ]
            ],
            [
                [
                    108,
                    565
                ],
                [
                    1109,
                    568
                ],
                [
                    1108,
                    595
                ],
                [
                    108,
                    592
                ]
            ],
            [
                [
                    111,
                    596
                ],
                [
                    797,
                    596
                ],
                [
                    797,
                    620
                ],
                [
                    111,
                    620
                ]
            ],
            [
                [
                    166,
                    620
                ],
                [
                    1103,
                    623
                ],
                [
                    1102,
                    649
                ],
                [
                    166,
                    646
                ]
            ],
            [
                [
                    110,
                    649
                ],
                [
                    826,
                    647
                ],
                [
                    826,
                    674
                ],
                [
                    110,
                    676
                ]
            ],
            [
                [
                    164,
                    674
                ],
                [
                    1104,
                    678
                ],
                [
                    1103,
                    706
                ],
                [
                    164,
                    702
                ]
            ],
            [
                [
                    110,
                    704
                ],
                [
                    1103,
                    705
                ],
                [
                    1103,
                    732
                ],
                [
                    110,
                    731
                ]
            ],
            [
                [
                    109,
                    732
                ],
                [
                    1100,
                    733
                ],
                [
                    1100,
                    760
                ],
                [
                    109,
                    759
                ]
            ],
            [
                [
                    109,
                    759
                ],
                [
                    1100,
                    760
                ],
                [
                    1100,
                    786
                ],
                [
                    109,
                    785
                ]
            ],
            [
                [
                    110,
                    788
                ],
                [
                    944,
                    789
                ],
                [
                    944,
                    813
                ],
                [
                    110,
                    812
                ]
            ],
            [
                [
                    366,
                    840
                ],
                [
                    415,
                    840
                ],
                [
                    415,
                    867
                ],
                [
                    366,
                    867
                ]
            ],
            [
                [
                    439,
                    842
                ],
                [
                    849,
                    842
                ],
                [
                    849,
                    866
                ],
                [
                    439,
                    866
                ]
            ],
            [
                [
                    166,
                    869
                ],
                [
                    1108,
                    873
                ],
                [
                    1107,
                    900
                ],
                [
                    166,
                    896
                ]
            ],
            [
                [
                    108,
                    900
                ],
                [
                    1107,
                    901
                ],
                [
                    1106,
                    924
                ],
                [
                    108,
                    923
                ]
            ],
            [
                [
                    110,
                    925
                ],
                [
                    1105,
                    925
                ],
                [
                    1105,
                    952
                ],
                [
                    110,
                    952
                ]
            ],
            [
                [
                    112,
                    955
                ],
                [
                    759,
                    955
                ],
                [
                    759,
                    979
                ],
                [
                    112,
                    979
                ]
            ],
            [
                [
                    151,
                    979
                ],
                [
                    1107,
                    983
                ],
                [
                    1106,
                    1010
                ],
                [
                    151,
                    1006
                ]
            ],
            [
                [
                    108,
                    1008
                ],
                [
                    1108,
                    1010
                ],
                [
                    1107,
                    1037
                ],
                [
                    108,
                    1035
                ]
            ],
            [
                [
                    111,
                    1040
                ],
                [
                    338,
                    1040
                ],
                [
                    338,
                    1060
                ],
                [
                    111,
                    1060
                ]
            ],
            [
                [
                    151,
                    1061
                ],
                [
                    1108,
                    1065
                ],
                [
                    1107,
                    1092
                ],
                [
                    151,
                    1088
                ]
            ],
            [
                [
                    109,
                    1093
                ],
                [
                    1108,
                    1093
                ],
                [
                    1108,
                    1117
                ],
                [
                    109,
                    1117
                ]
            ],
            [
                [
                    108,
                    1118
                ],
                [
                    1108,
                    1119
                ],
                [
                    1107,
                    1146
                ],
                [
                    108,
                    1145
                ]
            ],
            [
                [
                    110,
                    1147
                ],
                [
                    1106,
                    1149
                ],
                [
                    1105,
                    1173
                ],
                [
                    110,
                    1171
                ]
            ],
            [
                [
                    111,
                    1176
                ],
                [
                    1107,
                    1176
                ],
                [
                    1107,
                    1199
                ],
                [
                    111,
                    1199
                ]
            ],
            [
                [
                    111,
                    1203
                ],
                [
                    807,
                    1203
                ],
                [
                    807,
                    1227
                ],
                [
                    111,
                    1227
                ]
            ],
            [
                [
                    150,
                    1228
                ],
                [
                    1109,
                    1231
                ],
                [
                    1108,
                    1258
                ],
                [
                    150,
                    1255
                ]
            ],
            [
                [
                    109,
                    1256
                ],
                [
                    1108,
                    1259
                ],
                [
                    1107,
                    1285
                ],
                [
                    109,
                    1282
                ]
            ],
            [
                [
                    112,
                    1287
                ],
                [
                    638,
                    1287
                ],
                [
                    638,
                    1311
                ],
                [
                    112,
                    1311
                ]
            ],
            [
                [
                    150,
                    1309
                ],
                [
                    1108,
                    1311
                ],
                [
                    1107,
                    1340
                ],
                [
                    150,
                    1338
                ]
            ],
            [
                [
                    109,
                    1337
                ],
                [
                    407,
                    1338
                ],
                [
                    407,
                    1365
                ],
                [
                    109,
                    1364
                ]
            ],
            [
                [
                    146,
                    1367
                ],
                [
                    1011,
                    1370
                ],
                [
                    1011,
                    1394
                ],
                [
                    146,
                    1391
                ]
            ],
            [
                [
                    107,
                    1396
                ],
                [
                    1106,
                    1398
                ],
                [
                    1105,
                    1421
                ],
                [
                    107,
                    1419
                ]
            ],
            [
                [
                    111,
                    1423
                ],
                [
                    1106,
                    1425
                ],
                [
                    1105,
                    1449
                ],
                [
                    111,
                    1447
                ]
            ],
            [
                [
                    110,
                    1451
                ],
                [
                    1107,
                    1452
                ],
                [
                    1106,
                    1475
                ],
                [
                    110,
                    1474
                ]
            ],
            [
                [
                    111,
                    1479
                ],
                [
                    1107,
                    1479
                ],
                [
                    1107,
                    1502
                ],
                [
                    111,
                    1502
                ]
            ],
            [
                [
                    112,
                    1508
                ],
                [
                    322,
                    1508
                ],
                [
                    322,
                    1529
                ],
                [
                    112,
                    1529
                ]
            ],
            [
                [
                    110,
                    1566
                ],
                [
                    446,
                    1568
                ],
                [
                    446,
                    1588
                ],
                [
                    110,
                    1586
                ]
            ],
            [
                [
                    1079,
                    1564
                ],
                [
                    1101,
                    1564
                ],
                [
                    1101,
                    1591
                ],
                [
                    1079,
                    1591
                ]
            ]
        ],
        "rec_boxes": [
            [
                167,
                94,
                1101,
                124
            ],
            [
                112,
                124,
                394,
                150
            ],
            [
                166,
                149,
                1102,
                182
            ],
            [
                111,
                181,
                358,
                206
            ],
            [
                166,
                206,
                1101,
                235
            ],
            [
                112,
                236,
                668,
                260
            ],
            [
                165,
                261,
                1104,
                290
            ],
            [
                110,
                292,
                721,
                316
            ],
            [
                166,
                316,
                1109,
                346
            ],
            [
                109,
                345,
                1109,
                372
            ],
            [
                111,
                374,
                1108,
                398
            ],
            [
                111,
                404,
                214,
                425
            ],
            [
                203,
                403,
                376,
                427
            ],
            [
                363,
                399,
                921,
                428
            ],
            [
                927,
                403,
                959,
                422
            ],
            [
                970,
                401,
                1108,
                425
            ],
            [
                109,
                430,
                1108,
                454
            ],
            [
                112,
                458,
                1108,
                482
            ],
            [
                110,
                484,
                1109,
                510
            ],
            [
                110,
                512,
                1108,
                536
            ],
            [
                108,
                538,
                1109,
                566
            ],
            [
                108,
                565,
                1109,
                595
            ],
            [
                111,
                596,
                797,
                620
            ],
            [
                166,
                620,
                1103,
                649
            ],
            [
                110,
                647,
                826,
                676
            ],
            [
                164,
                674,
                1104,
                706
            ],
            [
                110,
                704,
                1103,
                732
            ],
            [
                109,
                732,
                1100,
                760
            ],
            [
                109,
                759,
                1100,
                786
            ],
            [
                110,
                788,
                944,
                813
            ],
            [
                366,
                840,
                415,
                867
            ],
            [
                439,
                842,
                849,
                866
            ],
            [
                166,
                869,
                1108,
                900
            ],
            [
                108,
                900,
                1107,
                924
            ],
            [
                110,
                925,
                1105,
                952
            ],
            [
                112,
                955,
                759,
                979
            ],
            [
                151,
                979,
                1107,
                1010
            ],
            [
                108,
                1008,
                1108,
                1037
            ],
            [
                111,
                1040,
                338,
                1060
            ],
            [
                151,
                1061,
                1108,
                1092
            ],
            [
                109,
                1093,
                1108,
                1117
            ],
            [
                108,
                1118,
                1108,
                1146
            ],
            [
                110,
                1147,
                1106,
                1173
            ],
            [
                111,
                1176,
                1107,
                1199
            ],
            [
                111,
                1203,
                807,
                1227
            ],
            [
                150,
                1228,
                1109,
                1258
            ],
            [
                109,
                1256,
                1108,
                1285
            ],
            [
                112,
                1287,
                638,
                1311
            ],
            [
                150,
                1309,
                1108,
                1340
            ],
            [
                109,
                1337,
                407,
                1365
            ],
            [
                146,
                1367,
                1011,
                1394
            ],
            [
                107,
                1396,
                1106,
                1421
            ],
            [
                111,
                1423,
                1106,
                1449
            ],
            [
                110,
                1451,
                1107,
                1475
            ],
            [
                111,
                1479,
                1107,
                1502
            ],
            [
                112,
                1508,
                322,
                1529
            ],
            [
                110,
                1566,
                446,
                1588
            ],
            [
                1079,
                1564,
                1101,
                1591
            ]
        ]
    }
}